EasyHTTPServerAJM/__init__.py
EasyHTTPServerAJM/_version.py
EasyHTTPServerAJM/easy_http_server.py
easyhttpserverajm-0.1.1.dist-info/licenses/LICENSE.txt
easyhttpserverajm-0.1.1.dist-info/METADATA
easyhttpserverajm-0.1.1.dist-info/WHEEL
easyhttpserverajm-0.1.1.dist-info/top_level.txt
easyhttpserverajm-0.1.1.dist-info/RECORD
