Metadata-Version: 2.4
Name: EasyHTTPServerAJM
Version: 0.1.1
Summary: quick and dirty http server
Home-page: https://github.com/amcsparron2793-Water/EasyHTTPServerAJM
Download-URL: https://github.com/amcsparron2793-Water/EasyHTTPServerAJM/archive/refs/tags/0.1.1.tar.gz
Author: Amcsparron
Author-email: amcsparron@albanyny.gov
License: MIT License
Classifier: Development Status :: 3 - Alpha
Classifier: Intended Audience :: Developers
Classifier: Topic :: Software Development :: Build Tools
Classifier: License :: OSI Approved :: MIT License
Classifier: Programming Language :: Python :: 3
License-File: LICENSE.txt
Dynamic: author
Dynamic: author-email
Dynamic: classifier
Dynamic: description
Dynamic: description-content-type
Dynamic: download-url
Dynamic: home-page
Dynamic: license
Dynamic: license-file
Dynamic: summary
